dydx4/__init__.py
dydx4/chain/__init__.py
dydx4/chain/aerial/__init__.py
dydx4/chain/aerial/client/__init__.py
dydx4/chain/aerial/client/bank.py
dydx4/chain/aerial/client/distribution.py
dydx4/chain/aerial/client/staking.py
dydx4/chain/aerial/client/utils.py
dydx4/chain/aerial/coins.py
dydx4/chain/aerial/config.py
dydx4/chain/aerial/exceptions.py
dydx4/chain/aerial/faucet.py
dydx4/chain/aerial/gas.py
dydx4/chain/aerial/tx.py
dydx4/chain/aerial/tx_helpers.py
dydx4/chain/aerial/urls.py
dydx4/chain/aerial/wallet.py
dydx4/chain/auth/__init__.py
dydx4/chain/auth/interface.py
dydx4/chain/auth/rest_client.py
dydx4/chain/bank/__init__.py
dydx4/chain/bank/interface.py
dydx4/chain/bank/rest_client.py
dydx4/chain/common/__init__.py
dydx4/chain/common/rest_client.py
dydx4/chain/common/types.py
dydx4/chain/common/utils.py
dydx4/chain/crypto/__init__.py
dydx4/chain/crypto/address.py
dydx4/chain/crypto/hashfuncs.py
dydx4/chain/crypto/interface.py
dydx4/chain/crypto/keypairs.py
dydx4/chain/crypto/keypairs_bls.py
dydx4/chain/distribution/__init__.py
dydx4/chain/distribution/interface.py
dydx4/chain/distribution/rest_client.py
dydx4/chain/evidence/__init__.py
dydx4/chain/evidence/interface.py
dydx4/chain/evidence/rest_client.py
dydx4/chain/gov/__init__.py
dydx4/chain/gov/interface.py
dydx4/chain/gov/rest_client.py
dydx4/chain/mint/__init__.py
dydx4/chain/mint/interface.py
dydx4/chain/mint/rest_client.py
dydx4/chain/params/__init__.py
dydx4/chain/params/interface.py
dydx4/chain/params/rest_client.py
dydx4/chain/slashing/__init__.py
dydx4/chain/slashing/interface.py
dydx4/chain/slashing/rest_client.py
dydx4/chain/staking/__init__.py
dydx4/chain/staking/interface.py
dydx4/chain/staking/rest_client.py
dydx4/chain/tendermint/__init__.py
dydx4/chain/tendermint/interface.py
dydx4/chain/tendermint/rest_client.py
dydx4/chain/tx/__init__.py
dydx4/chain/tx/interface.py
dydx4/chain/tx/rest_client.py
dydx4/chain/upgrade/__init__.py
dydx4/chain/upgrade/interface.py
dydx4-0.3.0.dist-info/LICENSE
dydx4-0.3.0.dist-info/METADATA
dydx4-0.3.0.dist-info/WHEEL
dydx4-0.3.0.dist-info/RECORD
