Metadata-Version: 2.1
Name: dydx4
Version: 0.3.0
Summary: dYdX v4 Client
License: BSL-1.1
Author: John Huang
Author-email: contact@dydx.exchange
Requires-Python: >=3.8,<4.0
Classifier: License :: Other/Proprietary License
Classifier: Programming Language :: Python :: 3
Classifier: Programming Language :: Python :: 3.8
Classifier: Programming Language :: Python :: 3.9
Classifier: Programming Language :: Python :: 3.10
Classifier: Programming Language :: Python :: 3.11
Requires-Dist: Cython (>=0.29.0,<0.30.0)
Requires-Dist: aiohttp (>=3.8.1,<4.0.0)
Requires-Dist: bech32 (>=1.2.0,<2.0.0)
Requires-Dist: bip_utils (>=2.7.0,<3.0.0)
Requires-Dist: brownie (>=0.5.0,<0.6.0)
Requires-Dist: cytoolz (>=0.12.1,<0.13.0)
Requires-Dist: dateparser (>=1.0.0,<2.0.0)
Requires-Dist: ecdsa (>=0.18.0,<0.19.0)
Requires-Dist: eth-account (>=0.9.0,<0.10.0)
Requires-Dist: eth_keys (>=0.4.0,<0.5.0)
Requires-Dist: grpcio (>=1.56,<2.0)
Requires-Dist: grpcio-tools (>=1.56,<2.0)
Requires-Dist: mpmath (>=1.3.0,<2.0.0)
Requires-Dist: protobuf (>=4.23,<5.0)
Requires-Dist: requests (>=2.31.0,<3.0.0)
Requires-Dist: six (>=1.16,<2.0)
Requires-Dist: sympy (>=1.12.0,<2.0.0)
Requires-Dist: web3 (>=6.5.0,<7.0.0)
Requires-Dist: websocket_client (>=1.6.1,<2.0.0)
